{
  "datter": "døtre",
  "røm": "drømmer",
  "dom": "dommer",
  "søm": "sømmer",
  "natt": "netter",
  "egen": "egne",
  "land": "land",
  "and": "ender",
  "hovedstad": "hovedsteder",
  "strand": "strender",
  "tang": "tenger",
  "tann": "tenner",
  "mann": "menn",
  "hand": "hender",
  "far": "fedre",
  "mor": "mødre",
  "bror": "brødre",
  "bok": "bøker",
  "fot": "føtter",
  "rot": "røtter",
  "bot": "bøter",
  "bonde": "bønder",
  "hånd": "hender",
  "datter": "døtre",
  "kne": "knær",
  "tre": "trær",
  "kle": "håndklær",
  "foto": "foto",
  "folk": "folk",
  "politi": "politi",
  "mål": "mål",
  "løp": "løp",
  "barn": "barn",
  "egg": "egg",
  "ips": "ips",
  "forhold": "forhold",
  "kamp": "kamper",
  "mulig": "mulige",
  "selskap": "selskap",
  "ansatt": "ansatte",
  "skriv": "skriv",
  "meter": "meter",
  "hjem": "hjem",
  "liv": "liv",
  "nett": "nett",
  "år": "år",
  "sted": "sted",
  "kort": "kort",
  "lag": "lag",
  "arbeid": "arbeid",
  "spørsmål": "spørsmål",
  "ting": "ting",
  "søk": "søk",
  "eksempel": "eksempel",
  "par": "par",
  "krav": "krav",
  "poeng": "poeng",
  "sykehus": "sykehus",
  "forslag": "forslag",
  "prosent": "prosent",
  "sentrum": "sentra",
  "hus": "hus"
}
